setup.py
src/codejam/__init__.py
src/codejam/codejam.py
src/codejam/helpers.py
src/codejam/parsers.py
src/pycodejam.egg-info/PKG-INFO
src/pycodejam.egg-info/SOURCES.txt
src/pycodejam.egg-info/dependency_links.txt
src/pycodejam.egg-info/top_level.txt
src/pycodejam.egg-info/zip-safe