Metadata-Version: 1.0
Name: pycodejam
Version: 1.2.0
Summary: This module provides helpers to run and parse CodeJam problems
Home-page: http://github.com/yanatan16/pycodejam
Author: Jon Eisen
Author-email: jon.m.eisen@gmail.com
License: MIT
Keywords: google code jam codejam competition problem
Platform: UNKNOWN
